Metadata-Version: 1.0
Name: sasdataframe
Version: 0.0.5
Summary: Import a SAS dataset into a Pandas dataframe
Home-page: http://www.upenn.edu
Author: Joe Dougherty
Author-email: josepd@wharton.upenn.edu
License: UNKNOWN
Platform: UNKNOWN
